onepassword_local_search/CliSimple.py
onepassword_local_search/CliSimple_test.py
onepassword_local_search/OnePassword.py
onepassword_local_search/__init__.py
onepassword_local_search/__main__.py
onepassword_local_search/__version__.py
onepassword_local_search/exceptions/Hook.py
onepassword_local_search/exceptions/ManagedException.py
onepassword_local_search/exceptions/__init__.py
onepassword_local_search/lib/__init__.py
onepassword_local_search/lib/optestlib.py
onepassword_local_search/lib/optestlib_test.py
onepassword_local_search/lib/utils.py
onepassword_local_search/lib/utils_test.py
onepassword_local_search/models/Cipher.py
onepassword_local_search/models/Item.py
onepassword_local_search/models/__init__.py
onepassword_local_search/services/AccountService.py
onepassword_local_search/services/AccountService_test.py
onepassword_local_search/services/ConfigFileService.py
onepassword_local_search/services/ConfigFileService_test.py
onepassword_local_search/services/CryptoService.py
onepassword_local_search/services/CryptoService_test.py
onepassword_local_search/services/SecondaryCryptoService.py
onepassword_local_search/services/SecondaryCryptoService_test.py
onepassword_local_search/services/StorageService.py
onepassword_local_search/services/StorageService_test.py
onepassword_local_search/services/__init__.py
onepassword_local_search-1.1.6.dist-info/LICENSE
onepassword_local_search-1.1.6.dist-info/METADATA
onepassword_local_search-1.1.6.dist-info/WHEEL
onepassword_local_search-1.1.6.dist-info/entry_points.txt
onepassword_local_search-1.1.6.dist-info/top_level.txt
onepassword_local_search-1.1.6.dist-info/RECORD
