Metadata-Version: 2.1
Name: onepassword-local-search
Version: 1.1.6
Summary: Simple 1Password CLI to list and decrypt secrets by querying the local sqlite database
Home-page: https://github.com/mickaelperrin/onepassword-local-search
Author: Mickaël Perrin
Author-email: dev@mickaelperrin.fr
License: GPLv3
Keywords: onepassword 1password cli password secrets
Classifier: License :: OSI Approved :: GNU General Public License v3 or later (GPLv3+)
Classifier: Development Status :: 4 - Beta
Classifier: Environment :: Console
Classifier: Intended Audience :: Information Technology
Classifier: Natural Language :: French
Classifier: Topic :: Security
Classifier: Topic :: Security :: Cryptography
Classifier: Topic :: Utilities
Classifier: Programming Language :: Python
Classifier: Programming Language :: Python :: 3
Classifier: Programming Language :: Python :: 3.7
Classifier: Programming Language :: Python :: Implementation :: CPython
Classifier: Programming Language :: Python :: Implementation :: PyPy
Requires-Python: >=3.7.0
License-File: LICENSE
Requires-Dist: cryptography (==36.0.1)
Requires-Dist: pyjwkest (==1.4.2)
Requires-Dist: pyotp (==2.6.0)
